Metadata-Version: 2.4
Name: featcopilot
Version: 0.2.0
Summary: Next-generation LLM-powered auto feature engineering framework with GitHub Copilot SDK
Author: FeatCopilot Contributors
License: MIT
Project-URL: Homepage, https://github.com/thinkall/featcopilot
Project-URL: Documentation, https://github.com/thinkall/featcopilot#readme
Project-URL: Repository, https://github.com/thinkall/featcopilot
Keywords: machine-learning,feature-engineering,automl,llm,copilot,data-science
Classifier: Development Status :: 4 - Beta
Classifier: Intended Audience :: Developers
Classifier: Intended Audience :: Science/Research
Classifier: License :: OSI Approved :: MIT License
Classifier: Programming Language :: Python :: 3
Classifier: Programming Language :: Python :: 3.9
Classifier: Programming Language :: Python :: 3.10
Classifier: Programming Language :: Python :: 3.11
Classifier: Programming Language :: Python :: 3.12
Classifier: Topic :: Scientific/Engineering :: Artificial Intelligence
Requires-Python: >=3.9
Requires-Dist: numpy>=1.21.0
Requires-Dist: pandas>=1.3.0
Requires-Dist: scipy>=1.7.0
Requires-Dist: scikit-learn>=1.0.0
Requires-Dist: pydantic>=2.0.0
Requires-Dist: joblib>=1.1.0
Provides-Extra: llm
Requires-Dist: github-copilot-sdk>=0.1.0; extra == "llm"
Requires-Dist: nest_asyncio>=1.5.0; extra == "llm"
Provides-Extra: litellm
Requires-Dist: litellm>=1.0.0; extra == "litellm"
Requires-Dist: nest_asyncio>=1.5.0; extra == "litellm"
Provides-Extra: timeseries
Requires-Dist: statsmodels>=0.13.0; extra == "timeseries"
Provides-Extra: feast
Requires-Dist: feast>=0.30.0; extra == "feast"
Provides-Extra: full
Requires-Dist: github-copilot-sdk>=0.1.0; extra == "full"
Requires-Dist: litellm>=1.0.0; extra == "full"
Requires-Dist: statsmodels>=0.13.0; extra == "full"
Requires-Dist: feast>=0.30.0; extra == "full"
Requires-Dist: nest_asyncio>=1.5.0; extra == "full"
Provides-Extra: benchmark
Requires-Dist: github-copilot-sdk>=0.1.0; extra == "benchmark"
Requires-Dist: statsmodels>=0.13.0; extra == "benchmark"
Requires-Dist: flaml[automl,blendsearch]>=2.0.0; extra == "benchmark"
Requires-Dist: autogluon.tabular>=1.0.0; extra == "benchmark"
Requires-Dist: h2o>=3.40.0; extra == "benchmark"
Provides-Extra: dev
Requires-Dist: pytest>=7.0.0; extra == "dev"
Requires-Dist: pytest-asyncio>=0.21.0; extra == "dev"
Requires-Dist: pytest-cov>=4.0.0; extra == "dev"
Requires-Dist: black>=23.0.0; extra == "dev"
Requires-Dist: ruff>=0.1.0; extra == "dev"
Requires-Dist: mypy>=1.0.0; extra == "dev"
Requires-Dist: pre-commit>=3.6.0; extra == "dev"
